HousingPricePrediction/__init__.py
HousingPricePrediction/exception.py
HousingPricePrediction/logger.py
HousingPricePrediction/components/__init__.py
HousingPricePrediction/components/data_ingestion.py
HousingPricePrediction/components/data_transformation.py
HousingPricePrediction/components/model_evaluation.py
HousingPricePrediction/components/model_trainer.py
HousingPricePrediction/utils/__init__.py
HousingPricePrediction/utils/utils.py
uniqueHousingPricePredictionMLOps-0.0.1.dist-info/LICENSE
uniqueHousingPricePredictionMLOps-0.0.1.dist-info/METADATA
uniqueHousingPricePredictionMLOps-0.0.1.dist-info/WHEEL
uniqueHousingPricePredictionMLOps-0.0.1.dist-info/top_level.txt
uniqueHousingPricePredictionMLOps-0.0.1.dist-info/RECORD
