Metadata-Version: 2.1
Name: uniqueHousingPricePredictionMLOps
Version: 0.0.1
Summary: A python package for connecting with database.
Home-page: https://github.com/Asang/HousingPricePredictionMLOps
Author: Asang
Author-email: asangkumar6666@gmail.com
Project-URL: Bug Tracker, https://github.com/Asang/HousingPricePredictionMLOps/issues
License-File: LICENSE
Requires-Dist: pytest
Requires-Dist: pandas
Requires-Dist: numpy
Requires-Dist: ensure
Requires-Dist: scikit-learn
